<archimate:ArchimateDiagramModel
    xmlns:xsi="http://www.w3.org/2001/XMLSchema-instance"
    xmlns:archimate="http://www.archimatetool.com/archimate"
    name="Belangrijkste verantwoordelijkheden + IV, huidige situatie 2017"
    id="f3c1dcb9">
  <children
      xsi:type="archimate:DiagramModelArchimateObject"
      id="6fab723b">
    <sourceConnections
        xsi:type="archimate:DiagramModelArchimateConnection"
        id="0989585f"
        source="6fab723b"
        target="594dce59">
      <archimateRelationship
          xsi:type="archimate:ServingRelationship"
          href="ServingRelationship_c564195e.xml#c564195e"/>
    </sourceConnections>
    <bounds
        x="1542"
        y="444"
        width="120"
        height="55"/>
    <archimateElement
        xsi:type="archimate:ApplicationComponent"
        href="ApplicationComponent_7be29e58.xml#7be29e58"/>
  </children>
  <children
      xsi:type="archimate:DiagramModelArchimateObject"
      id="28bc4f50">
    <sourceConnections
        xsi:type="archimate:DiagramModelArchimateConnection"
        id="5de6a49c"
        source="28bc4f50"
        target="082abfa4">
      <archimateRelationship
          xsi:type="archimate:ServingRelationship"
          href="ServingRelationship_bc8a86a5.xml#bc8a86a5"/>
    </sourceConnections>
    <bounds
        x="198"
        y="423"
        width="120"
        height="76"/>
    <archimateElement
        xsi:type="archimate:ApplicationComponent"
        href="ApplicationComponent_fc0db4ca.xml#fc0db4ca"/>
  </children>
  <children
      xsi:type="archimate:DiagramModelArchimateObject"
      id="101aa24b">
    <sourceConnections
        xsi:type="archimate:DiagramModelArchimateConnection"
        id="b09a1e6d"
        source="101aa24b"
        target="be5536e3">
      <archimateRelationship
          xsi:type="archimate:ServingRelationship"
          href="ServingRelationship_63b55952.xml#63b55952"/>
    </sourceConnections>
    <bounds
        x="792"
        y="444"
        width="120"
        height="55"/>
    <archimateElement
        xsi:type="archimate:ApplicationComponent"
        href="ApplicationComponent_010d7adb.xml#010d7adb"/>
  </children>
  <children
      xsi:type="archimate:DiagramModelArchimateObject"
      id="cf3bb65f">
    <sourceConnections
        xsi:type="archimate:DiagramModelArchimateConnection"
        id="796497bb"
        source="cf3bb65f"
        target="37575a00">
      <archimateRelationship
          xsi:type="archimate:ServingRelationship"
          href="ServingRelationship_e4bfcb98.xml#e4bfcb98"/>
    </sourceConnections>
    <bounds
        x="534"
        y="444"
        width="120"
        height="55"/>
    <archimateElement
        xsi:type="archimate:ApplicationComponent"
        href="ApplicationComponent_29680618.xml#29680618"/>
  </children>
  <children
      xsi:type="archimate:DiagramModelArchimateObject"
      id="ec328477">
    <sourceConnections
        xsi:type="archimate:DiagramModelArchimateConnection"
        id="4d448cbd"
        source="ec328477"
        target="e6ded77c">
      <archimateRelationship
          xsi:type="archimate:ServingRelationship"
          href="ServingRelationship_810fecce.xml#810fecce"/>
    </sourceConnections>
    <bounds
        x="365"
        y="444"
        width="120"
        height="55"/>
    <archimateElement
        xsi:type="archimate:ApplicationComponent"
        href="ApplicationComponent_d0fbf4e6.xml#d0fbf4e6"/>
  </children>
  <children
      xsi:type="archimate:DiagramModelArchimateObject"
      id="e6ded77c"
      targetConnections="4d448cbd">
    <bounds
        x="360"
        y="12"
        width="144"
        height="385"/>
    <children
        xsi:type="archimate:DiagramModelArchimateObject"
        id="671a3470">
      <bounds
          x="12"
          y="96"
          width="120"
          height="55"/>
      <archimateElement
          xsi:type="archimate:BusinessProcess"
          href="BusinessProcess_a317687c.xml#a317687c"/>
    </children>
    <children
        xsi:type="archimate:DiagramModelArchimateObject"
        id="bccbfe30">
      <bounds
          x="12"
          y="168"
          width="120"
          height="55"/>
      <archimateElement
          xsi:type="archimate:BusinessProcess"
          href="BusinessProcess_88948f5b.xml#88948f5b"/>
    </children>
    <archimateElement
        xsi:type="archimate:BusinessFunction"
        href="BusinessFunction_81d7c25f.xml#81d7c25f"/>
  </children>
  <children
      xsi:type="archimate:DiagramModelArchimateObject"
      id="7dc73a4e"
      targetConnections="462f2bc0">
    <bounds
        x="1368"
        y="12"
        width="145"
        height="385"/>
    <children
        xsi:type="archimate:DiagramModelArchimateObject"
        id="fcba8064">
      <bounds
          x="12"
          y="96"
          width="120"
          height="55"/>
      <archimateElement
          xsi:type="archimate:Product"
          href="Product_87c6a1c6.xml#87c6a1c6"/>
    </children>
    <children
        xsi:type="archimate:DiagramModelArchimateObject"
        id="c7ebb6ac">
      <bounds
          x="12"
          y="168"
          width="120"
          height="55"/>
      <archimateElement
          xsi:type="archimate:BusinessProcess"
          href="BusinessProcess_fa3b25b0.xml#fa3b25b0"/>
    </children>
    <children
        xsi:type="archimate:DiagramModelArchimateObject"
        id="905d4d14">
      <bounds
          x="12"
          y="240"
          width="120"
          height="55"/>
      <archimateElement
          xsi:type="archimate:BusinessProcess"
          href="BusinessProcess_5671fb93.xml#5671fb93"/>
    </children>
    <archimateElement
        xsi:type="archimate:BusinessFunction"
        href="BusinessFunction_23b91914.xml#23b91914"/>
  </children>
  <children
      xsi:type="archimate:DiagramModelArchimateObject"
      id="be5536e3"
      targetConnections="b09a1e6d">
    <bounds
        x="696"
        y="12"
        width="325"
        height="385"/>
    <children
        xsi:type="archimate:DiagramModelArchimateObject"
        id="36a29d0f">
      <bounds
          x="12"
          y="24"
          width="144"
          height="349"/>
      <children
          xsi:type="archimate:DiagramModelArchimateObject"
          id="3ea7b259">
        <bounds
            x="12"
            y="72"
            width="120"
            height="73"/>
        <archimateElement
            xsi:type="archimate:BusinessProcess"
            href="BusinessProcess_be61b5b5.xml#be61b5b5"/>
      </children>
      <children
          xsi:type="archimate:DiagramModelArchimateObject"
          id="0bd004ce">
        <bounds
            x="12"
            y="156"
            width="120"
            height="73"/>
        <archimateElement
            xsi:type="archimate:BusinessProcess"
            href="BusinessProcess_8f6ad1bd.xml#8f6ad1bd"/>
      </children>
      <children
          xsi:type="archimate:DiagramModelArchimateObject"
          id="13fb12b0">
        <bounds
            x="12"
            y="240"
            width="120"
            height="55"/>
        <archimateElement
            xsi:type="archimate:BusinessProcess"
            href="BusinessProcess_75bd277a.xml#75bd277a"/>
      </children>
      <archimateElement
          xsi:type="archimate:BusinessFunction"
          href="BusinessFunction_5b151a81.xml#5b151a81"/>
    </children>
    <children
        xsi:type="archimate:DiagramModelArchimateObject"
        id="01993146">
      <bounds
          x="168"
          y="24"
          width="144"
          height="349"/>
      <children
          xsi:type="archimate:DiagramModelArchimateObject"
          id="93f8bf8a">
        <bounds
            x="12"
            y="72"
            width="120"
            height="55"/>
        <archimateElement
            xsi:type="archimate:BusinessProcess"
            href="BusinessProcess_a2164c84.xml#a2164c84"/>
      </children>
      <children
          xsi:type="archimate:DiagramModelArchimateObject"
          id="425427a7">
        <bounds
            x="12"
            y="144"
            width="120"
            height="55"/>
        <archimateElement
            xsi:type="archimate:BusinessProcess"
            href="BusinessProcess_6b6119d4.xml#6b6119d4"/>
      </children>
      <archimateElement
          xsi:type="archimate:BusinessFunction"
          href="BusinessFunction_94f54476.xml#94f54476"/>
    </children>
    <archimateElement
        xsi:type="archimate:BusinessFunction"
        href="BusinessFunction_013ddfb5.xml#013ddfb5"/>
  </children>
  <children
      xsi:type="archimate:DiagramModelArchimateObject"
      id="082abfa4"
      targetConnections="5de6a49c">
    <bounds
        x="192"
        y="12"
        width="145"
        height="385"/>
    <children
        xsi:type="archimate:DiagramModelArchimateObject"
        id="7eb9a22f">
      <bounds
          x="12"
          y="96"
          width="120"
          height="55"/>
      <archimateElement
          xsi:type="archimate:BusinessProcess"
          href="BusinessProcess_8e258824.xml#8e258824"/>
    </children>
    <children
        xsi:type="archimate:DiagramModelArchimateObject"
        id="380ef86e">
      <bounds
          x="12"
          y="168"
          width="120"
          height="55"/>
      <archimateElement
          xsi:type="archimate:BusinessProcess"
          href="BusinessProcess_f060ddba.xml#f060ddba"/>
    </children>
    <children
        xsi:type="archimate:DiagramModelArchimateObject"
        id="5e5942e4">
      <bounds
          x="12"
          y="240"
          width="120"
          height="55"/>
      <archimateElement
          xsi:type="archimate:BusinessProcess"
          href="BusinessProcess_3aafeaf0.xml#3aafeaf0"/>
    </children>
    <archimateElement
        xsi:type="archimate:BusinessFunction"
        href="BusinessFunction_ebf4fc02.xml#ebf4fc02"/>
  </children>
  <children
      xsi:type="archimate:DiagramModelArchimateObject"
      id="37575a00"
      targetConnections="796497bb">
    <bounds
        x="528"
        y="12"
        width="145"
        height="385"/>
    <children
        xsi:type="archimate:DiagramModelArchimateObject"
        id="a9e11088">
      <bounds
          x="12"
          y="96"
          width="120"
          height="55"/>
      <archimateElement
          xsi:type="archimate:BusinessProcess"
          href="BusinessProcess_a60e9afb.xml#a60e9afb"/>
    </children>
    <children
        xsi:type="archimate:DiagramModelArchimateObject"
        id="65349c95">
      <bounds
          x="12"
          y="168"
          width="120"
          height="73"/>
      <archimateElement
          xsi:type="archimate:BusinessProcess"
          href="BusinessProcess_833f7148.xml#833f7148"/>
    </children>
    <children
        xsi:type="archimate:DiagramModelArchimateObject"
        id="7b1ffb4b">
      <bounds
          x="12"
          y="252"
          width="120"
          height="55"/>
      <archimateElement
          xsi:type="archimate:Product"
          href="Product_383cb0f5.xml#383cb0f5"/>
    </children>
    <archimateElement
        xsi:type="archimate:BusinessFunction"
        href="BusinessFunction_6ca248aa.xml#6ca248aa"/>
  </children>
  <children
      xsi:type="archimate:DiagramModelArchimateObject"
      id="594dce59"
      targetConnections="0989585f"
      fontColor="#808080"
      fillColor="#e2e0b6">
    <bounds
        x="1536"
        y="12"
        width="145"
        height="385"/>
    <children
        xsi:type="archimate:DiagramModelArchimateObject"
        id="4b432820">
      <bounds
          x="12"
          y="96"
          width="120"
          height="55"/>
      <archimateElement
          xsi:type="archimate:BusinessProcess"
          href="BusinessProcess_763d5dde.xml#763d5dde"/>
    </children>
    <children
        xsi:type="archimate:DiagramModelArchimateObject"
        id="bfe362ac">
      <bounds
          x="12"
          y="168"
          width="120"
          height="55"/>
      <archimateElement
          xsi:type="archimate:Product"
          href="Product_b3a597d7.xml#b3a597d7"/>
    </children>
    <children
        xsi:type="archimate:DiagramModelNote"
        id="1a9c20a0"
        textAlignment="1"
        content="In afwachting van nieuwe wetgeving">
      <bounds
          x="12"
          y="336"
          width="120"
          height="39"/>
    </children>
    <archimateElement
        xsi:type="archimate:BusinessFunction"
        href="BusinessFunction_15283c5e.xml#15283c5e"/>
  </children>
  <children
      xsi:type="archimate:DiagramModelNote"
      id="17c16d73"
      textAlignment="1"
      content="Verantwoordelijkheid / taakgebied / product&#xD;&#xA;">
    <bounds
        x="1692"
        y="12"
        width="121"
        height="62"/>
  </children>
  <children
      xsi:type="archimate:DiagramModelNote"
      id="2106284d"
      textAlignment="1"
      content="Primair taaksysteem">
    <bounds
        x="1685"
        y="444"
        width="121"
        height="26"/>
  </children>
  <children
      xsi:type="archimate:DiagramModelArchimateObject"
      id="53fc5de7">
    <sourceConnections
        xsi:type="archimate:DiagramModelArchimateConnection"
        id="462f2bc0"
        source="53fc5de7"
        target="7dc73a4e">
      <archimateRelationship
          xsi:type="archimate:ServingRelationship"
          href="ServingRelationship_b056fc55.xml#b056fc55"/>
    </sourceConnections>
    <sourceConnections
        xsi:type="archimate:DiagramModelArchimateConnection"
        id="1974f68c"
        source="53fc5de7"
        target="4fdc8bfb">
      <archimateRelationship
          xsi:type="archimate:ServingRelationship"
          href="ServingRelationship_a3700bf1.xml#a3700bf1"/>
    </sourceConnections>
    <bounds
        x="1265"
        y="444"
        width="120"
        height="55"/>
    <archimateElement
        xsi:type="archimate:ApplicationComponent"
        href="ApplicationComponent_2c23d3ff.xml#2c23d3ff"/>
  </children>
  <children
      xsi:type="archimate:DiagramModelArchimateObject"
      id="4fdc8bfb"
      targetConnections="1974f68c">
    <sourceConnections
        xsi:type="archimate:DiagramModelArchimateConnection"
        id="fa7508bd-9e8e-43bd-9fbf-14b221b65da4"
        source="4fdc8bfb"
        target="57cfaec8-c201-43a6-a83c-e536f3f2477f">
      <archimateRelationship
          xsi:type="archimate:AggregationRelationship"
          href="AggregationRelationship_3984eea1-1490-4734-8342-b3803f47a89c.xml#3984eea1-1490-4734-8342-b3803f47a89c"/>
    </sourceConnections>
    <bounds
        x="1044"
        y="12"
        width="301"
        height="385"/>
    <children
        xsi:type="archimate:DiagramModelArchimateObject"
        id="a022d4db"
        targetConnections="9e2eabb5 4b00c08e">
      <bounds
          x="12"
          y="312"
          width="120"
          height="55"/>
      <archimateElement
          xsi:type="archimate:BusinessProcess"
          href="BusinessProcess_f060ddba.xml#f060ddba"/>
    </children>
    <children
        xsi:type="archimate:DiagramModelArchimateObject"
        id="b0680fd5">
      <bounds
          x="12"
          y="240"
          width="120"
          height="55"/>
      <archimateElement
          xsi:type="archimate:Product"
          href="Product_2b72bef0.xml#2b72bef0"/>
    </children>
    <children
        xsi:type="archimate:DiagramModelArchimateObject"
        id="2921865c"
        targetConnections="a2f0e43e">
      <bounds
          x="168"
          y="168"
          width="120"
          height="55"/>
      <archimateElement
          xsi:type="archimate:Product"
          href="Product_b2ecce28.xml#b2ecce28"/>
    </children>
    <children
        xsi:type="archimate:DiagramModelArchimateObject"
        id="9f00334e"
        targetConnections="69c82033">
      <bounds
          x="168"
          y="240"
          width="120"
          height="55"/>
      <archimateElement
          xsi:type="archimate:Product"
          href="Product_e1d3c7cb.xml#e1d3c7cb"/>
    </children>
    <children
        xsi:type="archimate:DiagramModelArchimateObject"
        id="d1fb9d57">
      <sourceConnections
          xsi:type="archimate:DiagramModelArchimateConnection"
          id="a2f0e43e"
          source="d1fb9d57"
          target="2921865c">
        <archimateRelationship
            xsi:type="archimate:AggregationRelationship"
            href="AggregationRelationship_7056b587.xml#7056b587"/>
      </sourceConnections>
      <sourceConnections
          xsi:type="archimate:DiagramModelArchimateConnection"
          id="69c82033"
          source="d1fb9d57"
          target="9f00334e">
        <archimateRelationship
            xsi:type="archimate:AggregationRelationship"
            href="AggregationRelationship_b3955625.xml#b3955625"/>
      </sourceConnections>
      <bounds
          x="12"
          y="168"
          width="120"
          height="55"/>
      <archimateElement
          xsi:type="archimate:Product"
          href="Product_3b2de077.xml#3b2de077"/>
    </children>
    <children
        xsi:type="archimate:DiagramModelArchimateObject"
        id="a425999d">
      <bounds
          x="12"
          y="96"
          width="120"
          height="55"/>
      <archimateElement
          xsi:type="archimate:BusinessProcess"
          href="BusinessProcess_d4f1fb84.xml#d4f1fb84"/>
    </children>
    <children
        xsi:type="archimate:DiagramModelArchimateObject"
        id="d8bbca57">
      <bounds
          x="168"
          y="96"
          width="120"
          height="55"/>
      <archimateElement
          xsi:type="archimate:Product"
          href="Product_93344fb0.xml#93344fb0"/>
    </children>
    <children
        xsi:type="archimate:DiagramModelArchimateObject"
        id="bd55c318">
      <bounds
          x="12"
          y="59"
          width="276"
          height="24"/>
      <archimateElement
          xsi:type="archimate:Goal"
          href="Goal_ddfd97d7.xml#ddfd97d7"/>
    </children>
    <children
        xsi:type="archimate:DiagramModelArchimateObject"
        id="64631dfe">
      <bounds
          x="12"
          y="24"
          width="276"
          height="24"/>
      <archimateElement
          xsi:type="archimate:Goal"
          href="Goal_a015a0ef.xml#a015a0ef"/>
    </children>
    <children
        xsi:type="archimate:DiagramModelArchimateObject"
        id="57cfaec8-c201-43a6-a83c-e536f3f2477f"
        targetConnections="fa7508bd-9e8e-43bd-9fbf-14b221b65da4">
      <bounds
          x="168"
          y="312"
          width="120"
          height="55"/>
      <archimateElement
          xsi:type="archimate:BusinessFunction"
          href="BusinessFunction_993d8be0.xml#993d8be0"/>
    </children>
    <archimateElement
        xsi:type="archimate:BusinessFunction"
        href="BusinessFunction_8ecb9db5.xml#8ecb9db5"/>
  </children>
  <children
      xsi:type="archimate:DiagramModelArchimateObject"
      id="1d8f7b54"
      targetConnections="3c2533c6">
    <bounds
        x="24"
        y="12"
        width="144"
        height="385"/>
    <children
        xsi:type="archimate:DiagramModelArchimateObject"
        id="26be4354">
      <bounds
          x="12"
          y="96"
          width="120"
          height="55"/>
      <archimateElement
          xsi:type="archimate:BusinessProcess"
          href="BusinessProcess_9aefe314.xml#9aefe314"/>
    </children>
    <children
        xsi:type="archimate:DiagramModelArchimateObject"
        id="a911437e">
      <bounds
          x="12"
          y="168"
          width="120"
          height="55"/>
      <archimateElement
          xsi:type="archimate:Product"
          href="Product_56c6a096.xml#56c6a096"/>
    </children>
    <archimateElement
        xsi:type="archimate:BusinessFunction"
        href="BusinessFunction_6ce1594a.xml#6ce1594a"/>
  </children>
  <children
      xsi:type="archimate:DiagramModelArchimateObject"
      id="f596ea67">
    <sourceConnections
        xsi:type="archimate:DiagramModelArchimateConnection"
        id="3c2533c6"
        source="f596ea67"
        target="1d8f7b54">
      <archimateRelationship
          xsi:type="archimate:ServingRelationship"
          href="ServingRelationship_1d18a316.xml#1d18a316"/>
    </sourceConnections>
    <bounds
        x="29"
        y="444"
        width="120"
        height="55"/>
    <archimateElement
        xsi:type="archimate:ApplicationComponent"
        href="ApplicationComponent_2622b9da.xml#2622b9da"/>
  </children>
  <children
      xsi:type="archimate:DiagramModelArchimateObject"
      id="8afaed36">
    <sourceConnections
        xsi:type="archimate:DiagramModelArchimateConnection"
        id="9e2eabb5"
        source="8afaed36"
        target="a022d4db">
      <archimateRelationship
          xsi:type="archimate:ServingRelationship"
          href="ServingRelationship_710670d6.xml#710670d6"/>
    </sourceConnections>
    <bounds
        x="1121"
        y="444"
        width="120"
        height="55"/>
    <archimateElement
        xsi:type="archimate:ApplicationComponent"
        href="ApplicationComponent_51c7b32b.xml#51c7b32b"/>
  </children>
  <children
      xsi:type="archimate:DiagramModelArchimateObject"
      id="51f8ac95">
    <sourceConnections
        xsi:type="archimate:DiagramModelArchimateConnection"
        id="4b00c08e"
        source="51f8ac95"
        target="a022d4db">
      <archimateRelationship
          xsi:type="archimate:ServingRelationship"
          href="ServingRelationship_3309bd18.xml#3309bd18"/>
    </sourceConnections>
    <bounds
        x="977"
        y="444"
        width="120"
        height="55"/>
    <archimateElement
        xsi:type="archimate:ApplicationComponent"
        href="ApplicationComponent_2d75d460.xml#2d75d460"/>
  </children>
</archimate:ArchimateDiagramModel>
